[
  {
    "userId": "test-user-1767625312484",
    "balance": 10,
    "currency": "GHS",
    "createdAt": "2026-01-05T15:01:52.500Z",
    "lastUpdated": "2026-01-05T15:01:52.500Z",
    "bonus": 10,
    "bonusGivenAt": "2026-01-05T15:01:52.500Z"
  },
  {
    "userId": "test-user-1767627188515",
    "balance": 50,
    "currency": "GHS",
    "createdAt": "2026-01-05T15:33:08.537Z",
    "transactions": [
      {
        "type": "add",
        "amount": 50,
        "reason": "Test add funds",
        "adminEmail": "admin@test.com",
        "timestamp": "2026-01-05T15:33:08.537Z",
        "previousBalance": 0,
        "newBalance": 50
      }
    ],
    "lastUpdated": "2026-01-05T15:33:08.537Z"
  },
  {
    "userId": "test-user-1767627927035",
    "balance": 50,
    "currency": "GHS",
    "createdAt": "2026-01-05T15:45:27.054Z",
    "transactions": [
      {
        "type": "add",
        "amount": 50,
        "reason": "Test add funds",
        "adminEmail": "admin@test.com",
        "timestamp": "2026-01-05T15:45:27.055Z",
        "previousBalance": 0,
        "newBalance": 50
      }
    ],
    "lastUpdated": "2026-01-05T15:45:27.055Z"
  },
  {
    "userId": "test-user-1767627933802",
    "balance": 0,
    "currency": "GHS",
    "createdAt": "2026-01-05T15:45:34.109Z",
    "transactions": [
      {
        "type": "deduct",
        "amount": 50,
        "reason": "Test deduct funds",
        "adminEmail": "admin@test.com",
        "timestamp": "2026-01-05T15:45:34.110Z",
        "previousBalance": 0,
        "newBalance": 0
      }
    ],
    "lastUpdated": "2026-01-05T15:45:34.110Z"
  },
  {
    "userId": "test-user-123",
    "balance": 100,
    "currency": "GHS",
    "createdAt": "2026-01-05T16:02:48.511Z",
    "transactions": [
      {
        "type": "add",
        "amount": 50,
        "reason": "Test from HTML page",
        "adminEmail": "test@admin.com",
        "timestamp": "2026-01-05T16:02:48.512Z",
        "previousBalance": 0,
        "newBalance": 50
      },
      {
        "type": "add",
        "amount": 50,
        "reason": "Test from HTML page",
        "adminEmail": "test@admin.com",
        "timestamp": "2026-01-05T16:03:39.374Z",
        "previousBalance": 50,
        "newBalance": 100
      }
    ],
    "lastUpdated": "2026-01-05T16:03:39.374Z"
  }
]